py_template_engine/RenderError.py
py_template_engine/TemplateEngine.py
py_template_engine/TemplaterInterface.py
py_template_engine/__init__.py
py_template_engine/sub_engines/EachTemplater.py
py_template_engine/sub_engines/FunctionTemplater.py
py_template_engine/sub_engines/IfTemplater.py
py_template_engine/sub_engines/IncludeTemplater.py
py_template_engine/sub_engines/RenderTemplater.py
py_template_engine/sub_engines/VariableTemplater.py
py_template_engine/sub_engines/__init__.py
py_template_engine-0.2.6.dist-info/licenses/LICENSE
py_template_engine-0.2.6.dist-info/METADATA
py_template_engine-0.2.6.dist-info/WHEEL
py_template_engine-0.2.6.dist-info/top_level.txt
py_template_engine-0.2.6.dist-info/RECORD
