Metadata-Version: 2.4
Name: py-template-engine
Version: 0.2.6
Summary: A Python template engine with support for variables, functions, conditionals, loops, and includes
Author-email: Yannick Zimmermann <yannick.zimmermann@proton.me>
License: MIT
Project-URL: Homepage, https://github.com/zimmer-yan/py-template-engine
Project-URL: Repository, https://github.com/zimmer-yan/py-template-engine
Project-URL: Documentation, https://github.com/zimmer-yan/py-template-engine#readme
Project-URL: Bug Tracker, https://github.com/zimmer-yan/py-template-engine/issues
Keywords: template,templating,engine,jinja,mustache,handlebars
Classifier: Development Status :: 3 - Alpha
Classifier: Intended Audience :: Developers
Classifier: Programming Language :: Python :: 3
Classifier: Programming Language :: Python :: 3.8
Classifier: Programming Language :: Python :: 3.9
Classifier: Programming Language :: Python :: 3.10
Classifier: Programming Language :: Python :: 3.11
Classifier: Programming Language :: Python :: 3.12
Requires-Python: >=3.8
License-File: LICENSE
Provides-Extra: dev
Requires-Dist: pytest>=7.0.0; extra == "dev"
Requires-Dist: pytest-cov>=2.0; extra == "dev"
Requires-Dist: black>=22.0.0; extra == "dev"
Requires-Dist: flake8>=5.0.0; extra == "dev"
Requires-Dist: mypy>=0.991; extra == "dev"
Dynamic: license-file
